<annotation>
    <folder>no-nav</folder>
    <filename>screencapture-primelineauto-certified-Kia-2013-Kia-Forte-1cabe78a0a0e0a3a6fa1794949f80a8e-htm-2018-12-03-12_28_01.jpg</filename>
    <size>
        <width>1677</width>
        <height>1784</height>
        <depth>3</depth>
    </size>
    <segmented>0</segmented>
    <object>
        <name>car</name>
        <pose>Unspecified</pose>
        <truncated>0</truncated>
        <occluded>0</occluded>
        <difficult>0</difficult>
        <bndbox>
            <xmin>969</xmin>
            <ymin>779</ymin>
            <xmax>987</xmax>
            <ymax>808</ymax>
        </bndbox>
    </object>
</annotation>