<annotation>
    <folder>no-nav</folder>
    <filename>screencapture-autotrader-ca-a-Volkswagen-Golf-Wagon-Ottawa-Ontario-5_41113753_20151103120223859-2018-12-12-17_01_29.jpg</filename>
    <size>
        <width>1472</width>
        <height>3451</height>
        <depth>3</depth>
    </size>
    <segmented>0</segmented>
    <object>
        <name>car</name>
        <pose>Unspecified</pose>
        <truncated>0</truncated>
        <occluded>0</occluded>
        <difficult>0</difficult>
        <bndbox>
            <xmin>890</xmin>
            <ymin>592</ymin>
            <xmax>911</xmax>
            <ymax>614</ymax>
        </bndbox>
    </object>
</annotation>