<annotation>
    <folder>nav</folder>
    <filename>screencapture-woodstockhyundai-used-vehicle-2018-nissan-sentra-18-sv-id9070473-htm-2018-12-14-11_06_50.jpg</filename>
    <size>
        <width>1472</width>
        <height>2840</height>
        <depth>3</depth>
    </size>
    <segmented>0</segmented>
    <object>
        <name>car</name>
        <pose>Unspecified</pose>
        <truncated>0</truncated>
        <occluded>0</occluded>
        <difficult>0</difficult>
        <bndbox>
            <xmin>828</xmin>
            <ymin>977</ymin>
            <xmax>833</xmax>
            <ymax>985</ymax>
        </bndbox>
    </object>
</annotation>