<annotation>
    <folder>nav</folder>
    <filename>screencapture-palladinohonda-inventory-used-2014-kia-forte-ex-manual-back-up-camera-cruise-control-fwd-4dr-car-knafx4a89e5169796-2018-12-14-12_21_42.jpg</filename>
    <size>
        <width>1472</width>
        <height>3143</height>
        <depth>3</depth>
    </size>
    <segmented>0</segmented>
    <object>
        <name>car</name>
        <pose>Unspecified</pose>
        <truncated>0</truncated>
        <occluded>0</occluded>
        <difficult>0</difficult>
        <bndbox>
            <xmin>944</xmin>
            <ymin>929</ymin>
            <xmax>956</xmax>
            <ymax>947</ymax>
        </bndbox>
    </object>
</annotation>